CHANGELOG.md
LICENSE
MANIFEST.in
README.md
_build.py
pyproject.toml
setup.py
src/.clang-format
src/CMakeLists.txt
src/alphaindex.cpp
src/appendable.cpp
src/caniter.cpp
src/casemap.cpp
src/char16ptr.cpp
src/char16ptr.hpp
src/coleitr.cpp
src/compactdecimalformat.cpp
src/currpinf.cpp
src/currunit.cpp
src/datefmt.cpp
src/dcfmtsym.cpp
src/decimfmt.cpp
src/displayoptions.cpp
src/dtfmtsym.cpp
src/dtintrv.cpp
src/dtitvfmt.cpp
src/dtitvinf.cpp
src/dtptngen.cpp
src/dtrule.cpp
src/edits.cpp
src/errorcode.cpp
src/fieldpos.cpp
src/filteredbrk.cpp
src/fmtable.cpp
src/format.cpp
src/formattedvalue.cpp
src/fpositer.cpp
src/gender.cpp
src/gregocal.cpp
src/icudataver.cpp
src/idna.cpp
src/listformatter.cpp
src/localebuilder.cpp
src/localematcher.cpp
src/locdspnm.cpp
src/locid.cpp
src/main.cpp
src/main.hpp
src/measfmt.cpp
src/measunit.cpp
src/measure.cpp
src/messagepattern.cpp
src/msgfmt.cpp
src/normalizer2.cpp
src/nounit.cpp
src/numberformatter.cpp
src/numberrangeformatter.cpp
src/numfmt.cpp
src/numsys.cpp
src/parseerr.cpp
src/parsepos.cpp
src/plurfmt.cpp
src/plurrule.cpp
src/rbbi.cpp
src/rbnf.cpp
src/regex.cpp
src/region.cpp
src/reldatefmt.cpp
src/resbund.cpp
src/schriter.cpp
src/scientificnumberformatter.cpp
src/selfmt.cpp
src/simplenumberformatter.cpp
src/smpdtfmt.cpp
src/sortkey.cpp
src/strenum.cpp
src/stringoptions.cpp
src/stsearch.cpp
src/tblcoll.cpp
src/timezone.cpp
src/tmunit.cpp
src/translit.cpp
src/tzfmt.cpp
src/tznames.cpp
src/tzrule.cpp
src/tztrans.cpp
src/ubidi.cpp
src/ubidiptr.hpp
src/ubiditransform.cpp
src/ubiditransformptr.hpp
src/ubrk.cpp
src/ucal.cpp
src/uchar.cpp
src/ucnv.cpp
src/ucnv_cb.cpp
src/ucnv_err.cpp
src/ucnv_err.hpp
src/ucol.cpp
src/ucpmap.cpp
src/ucpmapptr.hpp
src/ucsdet.cpp
src/ucsdetptr.hpp
src/ucurr.cpp
src/udat.cpp
src/udatpg.cpp
src/udisplaycontext.cpp
src/udisplayoptions.cpp
src/uenum.cpp
src/uenumptr.hpp
src/uformattedvalue.cpp
src/ugender.cpp
src/uidna.cpp
src/uldnames.cpp
src/ulistformatter.cpp
src/uloc.cpp
src/ulocdata.cpp
src/ulocdataptr.hpp
src/icupy.egg-info/PKG-INFO
src/icupy.egg-info/SOURCES.txt
src/icupy.egg-info/dependency_links.txt
src/icupy.egg-info/top_level.txt
