Metadata-Version: 2.2
Name: icupy
Version: 0.21.0
Summary: Python bindings for ICU4C
Author-email: Tetsuya Miura <miute.dev@gmail.com>
License: MIT License
Project-URL: ICU, https://icu.unicode.org/home
Project-URL: Download, https://github.com/miute/icupy/releases
Project-URL: Repository, https://github.com/miute/icupy
Project-URL: Changelog, https://github.com/miute/icupy/blob/main/CHANGELOG.md
Keywords: icu4c,unicode,binding
Classifier: Development Status :: 4 - Beta
Classifier: Intended Audience :: Developers
Classifier: License :: OSI Approved :: MIT License
Classifier: Operating System :: Microsoft :: Windows
Classifier: Operating System :: POSIX
Classifier: Programming Language :: C++
Classifier: Programming Language :: Python :: 3 :: Only
Classifier: Programming Language :: Python :: 3.9
Classifier: Programming Language :: Python :: 3.10
Classifier: Programming Language :: Python :: 3.11
Classifier: Programming Language :: Python :: 3.12
Classifier: Programming Language :: Python :: 3.13
Classifier: Programming Language :: Python :: Implementation :: CPython
Classifier: Topic :: Software Development :: Internationalization
Classifier: Topic :: Software Development :: Localization
Requires-Python: >=3.9
License-File: LICENSE
